funPIL/__init__.py
funPIL/funPIL.py
funPIL-0.0.8.dist-info/LICENSE
funPIL-0.0.8.dist-info/METADATA
funPIL-0.0.8.dist-info/WHEEL
funPIL-0.0.8.dist-info/top_level.txt
funPIL-0.0.8.dist-info/RECORD
