Metadata-Version: 2.1
Name: funPIL
Version: 0.0.8
Home-page: https://github.com/DeusAres/funPIL
Author: DeusAres
Classifier: Programming Language :: Python :: 3
Classifier: Operating System :: OS Independent
License-File: LICENSE
